[ {
  "name" : "ChangePassword",
  "type" : "PAGE",
  "params" : [ {
    "name" : "email",
    "type" : "string"
  } ]
}, {
  "name" : "ChangePasswordSuccess",
  "type" : "PAGE",
  "params" : [ ]
}, {
  "name" : "Common",
  "type" : "PARTIAL",
  "params" : [ ]
}, {
  "name" : "DashboardSuratKuasa",
  "type" : "PAGE",
  "params" : [ ]
}, {
  "name" : "FAQ",
  "type" : "PAGE",
  "params" : [ ]
}, {
  "name" : "FAQPartial",
  "type" : "PARTIAL",
  "params" : [ {
    "name" : "id",
    "type" : "integer"
  } ]
}, {
  "name" : "ForgotPassword",
  "type" : "PAGE",
  "params" : [ ]
}, {
  "name" : "ForgotPasswordLinkSent",
  "type" : "PAGE",
  "params" : [ ]
}, {
  "name" : "Leaderboards",
  "type" : "PAGE",
  "params" : [ ]
}, {
  "name" : "Login",
  "type" : "PAGE",
  "params" : [ ]
}, {
  "name" : "Main",
  "type" : "PAGE",
  "params" : [ ]
}, {
  "name" : "MainPage",
  "type" : "PAGE",
  "params" : [ ]
}, {
  "name" : "ManageBadgesConfiguration",
  "type" : "PAGE",
  "params" : [ ]
}, {
  "name" : "ManagePointConfiguration",
  "type" : "PAGE",
  "params" : [ ]
}, {
  "name" : "RewardManagement",
  "type" : "PAGE",
  "params" : [ ]
}, {
  "name" : "SKAuction",
  "type" : "PAGE",
  "params" : [ ]
}, {
  "name" : "SKExtension",
  "type" : "PAGE",
  "params" : [ {
    "name" : "idParam",
    "type" : "integer"
  } ]
}, {
  "name" : "SKReqDetail",
  "type" : "PAGE",
  "params" : [ {
    "name" : "noAggr",
    "type" : "string"
  } ]
}, {
  "name" : "SKRequest",
  "type" : "PAGE",
  "params" : [ {
    "name" : "idParam",
    "type" : "integer"
  } ]
}, {
  "name" : "Sayembara",
  "type" : "PAGE",
  "params" : [ ]
}, {
  "name" : "SignIn",
  "type" : "PAGE",
  "params" : [ ]
}, {
  "name" : "SubmittedInformation",
  "type" : "PAGE",
  "params" : [ ]
}, {
  "name" : "SubmittedInformation1",
  "type" : "PAGE",
  "params" : [ {
    "name" : "idParam",
    "type" : "integer"
  } ]
}, {
  "name" : "SuratKuasaLelang",
  "type" : "PAGE",
  "params" : [ ]
}, {
  "name" : "SuratKuasaPermintaan",
  "type" : "PAGE",
  "params" : [ ]
}, {
  "name" : "SuratKuasaPermintaanDetail",
  "type" : "PARTIAL",
  "params" : [ {
    "name" : "no_aggr",
    "type" : "string"
  }, {
    "name" : "coll_cd",
    "type" : "string"
  } ]
}, {
  "name" : "SuratKuasaPermintaanPerpanjang",
  "type" : "PAGE",
  "params" : [ ]
}, {
  "name" : "SuratKuasaPerpajangnDetail",
  "type" : "PARTIAL",
  "params" : [ {
    "name" : "no_aggr",
    "type" : "string"
  }, {
    "name" : "coll_cd",
    "type" : "string"
  } ]
}, {
  "name" : "UserManagementInformant",
  "type" : "PAGE",
  "params" : [ ]
}, {
  "name" : "UserManagementMitra",
  "type" : "PAGE",
  "params" : [ ]
}, {
  "name" : "UserManagementPool",
  "type" : "PAGE",
  "params" : [ ]
}, {
  "name" : "UserManagementRemo",
  "type" : "PAGE",
  "params" : [ ]
}, {
  "name" : "footer",
  "type" : "FOOTER",
  "params" : [ ]
}, {
  "name" : "header",
  "type" : "HEADER",
  "params" : [ ]
}, {
  "name" : "leftPanel",
  "type" : "LEFTNAV",
  "params" : [ ]
}, {
  "name" : "leftnav",
  "type" : "LEFTNAV",
  "params" : [ ]
}, {
  "name" : "rightnav",
  "type" : "RIGHTNAV",
  "params" : [ ]
}, {
  "name" : "topnav",
  "type" : "TOPNAV",
  "params" : [ ]
} ]